randomfactory/__init__.py
randomfactory/main.py
randomfactory/test.py
randomfactory-1.0.8.dist-info/METADATA
randomfactory-1.0.8.dist-info/WHEEL
randomfactory-1.0.8.dist-info/entry_points.txt
randomfactory-1.0.8.dist-info/RECORD
