Metadata-Version: 2.1
Name: randomfactory
Version: 1.0.8
Summary: randomfactory is a helper function for generating random output that is used in testcase.
Home-page: https://github.com/codetree21/randomfactory
License: MIT
Author: chavokim
Author-email: treeboy0384@gmail.com
Requires-Python: >=3.8,<4.0
Classifier: License :: OSI Approved :: MIT License
Classifier: Programming Language :: Python :: 3
Classifier: Programming Language :: Python :: 3.8
Classifier: Programming Language :: Python :: 3.9
Classifier: Programming Language :: Python :: 3.10
Classifier: Programming Language :: Python :: 3.11
Project-URL: Repository, https://github.com/codetree21/randomfactory
